[
    {
        "id":1,
        "title":"REÇBER - Data Kablosu HF Cat6 U/FTP 500mt Gri",
        "price": 12.84,
        "image": "https://www.zeybekmarket.com/hcs-uftp-cat6a-lsoh-500mt-data-lan-kablolari-8548-66-B.jpg"
    },
    
    {
        "id":2,
        "title":"REÇBER - Data Kablosu Pvc CAT6 U/UTP 23AWG RIB 305mt Gri",
        "price": 7.83,
        "image": "https://n11scdn.akamaized.net/a1/602_857/01/78/50/05/IMG-6181414056254390934.jpg"
    
    },
    
    {
        "id":3,
        "title":"REÇBER - Sinyal Kablosu Hf 2x0,75 LIHCH 1000mt",
        "price": 62.30,
        "image": "https://st2.myideasoft.com/idea/be/68/myassets/products/118/lihch-tp-kablopiyasa.jpg?revision=1563968622"
    
    },
    
    {
        "id":4,
        "title":"REÇBER - Sinyal Kablosu HF 3x0,75 LIHCH 500mt",
        "price": 52.00,
        "image": "https://st3.myideasoft.com/shop/ad/07/myassets/products/214/29012015032032.jpg?revision=1638865237"
    },
    
    {
        "id":5,
        "title":"CATA - CT-4242G Led Ampul 40W E27 Günışığı",
        "price": 32.10,
        "image": "https://st.myideasoft.com/idea/be/68/myassets/products/313/sl500-ff23-lszh-cat6a-kablopiyasa.jpg?revision=1565945275"
    
    },
    
    {
        "id":6,
        "title":"REÇBER - Data Kablosu Pvc CAT5e F/UTP 24AWG 500mt",
        "price": 7.43,
        "image": "https://www.starakim.com/-12985-12-B.jpg"
    },
    {
        "id":7,
        "title":"REÇBER - Sinyal Kablosu HF 4x1,5 LIHCH 500mt",
        "price": 22.23,
        "image": "https://st3.myideasoft.com/shop/ad/07/myassets/products/214/29012015032032.jpg?revision=1638865237"
    }
    
    
    ]